ddaclient.py
simple_logger.py
ddaclient-1.1.13.dist-info/METADATA
ddaclient-1.1.13.dist-info/WHEEL
ddaclient-1.1.13.dist-info/entry_points.txt
ddaclient-1.1.13.dist-info/top_level.txt
ddaclient-1.1.13.dist-info/RECORD
