Metadata-Version: 2.1
Name: ddaclient
Version: 1.1.13
Summary: client for data-analysis services
Home-page: UNKNOWN
License: Creative Commons Attribution-Noncommercial-Share Alike license
Platform: UNKNOWN
Requires-Dist: python-shell-colors (>=0.2.1)
Requires-Dist: astropy
Requires-Dist: requests
